zigent/__init__.py
zigent/utils.py
zigent/actions/BaseAction.py
zigent/actions/InnerActions.py
zigent/actions/__init__.py
zigent/agent_prompts/BasePrompt.py
zigent/agent_prompts/__init__.py
zigent/agent_prompts/prompt_utils.py
zigent/agents/ABCAgent.py
zigent/agents/BaseAgent.py
zigent/agents/ManagerAgent.py
zigent/agents/__init__.py
zigent/agents/agent_utils.py
zigent/commons/AgentAct.py
zigent/commons/TaskPackage.py
zigent/commons/__init__.py
zigent/llm/LLMConfig.py
zigent/llm/__init__.py
zigent/llm/agent_llms.py
zigent/logging/BaseLogger.py
zigent/logging/__init__.py
zigent/logging/base.py
zigent/logging/multi_agent_log.py
zigent/logging/streamlit_log.py
zigent/logging/streamlit_logger.py
zigent/logging/terminal_logger.py
zigent/logging/utils.py
zigent/memory/AgentSTMemory.py
zigent/memory/__init__.py
zigent/memory/memory_utils.py
zigent-0.0.4.dist-info/LICENSE.txt
zigent-0.0.4.dist-info/METADATA
zigent-0.0.4.dist-info/WHEEL
zigent-0.0.4.dist-info/top_level.txt
zigent-0.0.4.dist-info/RECORD
