Metadata-Version: 2.2
Name: zigent
Version: 0.0.4
Summary: AI Agent for zishu.co.
Home-page: https://github.com/zigent/zigent
Author: Zhiwei Liu, Qi Hu
Author-email: zhiweiliu@salesforce.com, huqi1024@gmail.com
License: Apache License 2.0
Requires-Python: >=3.9
License-File: LICENSE.txt
Requires-Dist: openai==1.58.1
Requires-Dist: pydantic==2.10.4
Requires-Dist: black==24.10.0
Requires-Dist: numpy==2.2.1
Requires-Dist: wikipedia==1.4.0
Requires-Dist: duckduckgo-search==7.1.1
Requires-Dist: openmeteo_requests==1.3.0
Requires-Dist: requests_cache==1.2.1
Requires-Dist: retry_requests==2.0.0
Requires-Dist: python-dotenv==1.0.1
Requires-Dist: streamlit==1.41.1
Dynamic: author
Dynamic: author-email
Dynamic: description
Dynamic: description-content-type
Dynamic: home-page
Dynamic: license
Dynamic: requires-dist
Dynamic: requires-python
Dynamic: summary
